aluvia_sdk/__init__.py
aluvia_sdk/errors.py
aluvia_sdk/py.typed
aluvia_sdk/api/__init__.py
aluvia_sdk/api/account.py
aluvia_sdk/api/aluvia_api.py
aluvia_sdk/api/geos.py
aluvia_sdk/api/request.py
aluvia_sdk/api/types.py
aluvia_sdk/client/__init__.py
aluvia_sdk/client/adapters.py
aluvia_sdk/client/aluvia_client.py
aluvia_sdk/client/config_manager.py
aluvia_sdk/client/logger.py
aluvia_sdk/client/proxy_server.py
aluvia_sdk/client/rules.py
aluvia_sdk/client/types.py
aluvia_sdk-1.0.2.dist-info/licenses/LICENSE
aluvia_sdk-1.0.2.dist-info/METADATA
aluvia_sdk-1.0.2.dist-info/WHEEL
aluvia_sdk-1.0.2.dist-info/top_level.txt
aluvia_sdk-1.0.2.dist-info/RECORD
