Metadata-Version: 2.4
Name: aluvia-sdk
Version: 1.0.2
Summary: Aluvia SDK for Python - local smart proxy for automation workloads and AI agents
Author-email: Aluvia <support@aluvia.io>
License-Expression: MIT
Project-URL: Homepage, https://aluvia.io
Project-URL: Documentation, https://docs.aluvia.io
Project-URL: Repository, https://github.com/aluvia-connect/sdk-python
Project-URL: Issues, https://github.com/aluvia-connect/sdk-python/issues
Keywords: proxy,ai-agent,playwright,selenium,aluvia,web-scraping
Classifier: Development Status :: 5 - Production/Stable
Classifier: Intended Audience :: Developers
Classifier: Programming Language :: Python :: 3
Classifier: Programming Language :: Python :: 3.9
Classifier: Programming Language :: Python :: 3.10
Classifier: Programming Language :: Python :: 3.11
Classifier: Programming Language :: Python :: 3.12
Classifier: Topic :: Internet :: Proxy Servers
Classifier: Topic :: Software Development :: Libraries :: Python Modules
Requires-Python: >=3.9
License-File: LICENSE
Requires-Dist: httpx>=0.24.0
Requires-Dist: aiohttp>=3.8.0
Requires-Dist: proxy.py>=2.4.0
Provides-Extra: playwright
Requires-Dist: playwright>=1.40.0; extra == "playwright"
Provides-Extra: selenium
Requires-Dist: selenium>=4.0.0; extra == "selenium"
Provides-Extra: dev
Requires-Dist: pytest>=7.0.0; extra == "dev"
Requires-Dist: pytest-asyncio>=0.21.0; extra == "dev"
Requires-Dist: pytest-mock>=3.12.0; extra == "dev"
Requires-Dist: mypy>=1.0.0; extra == "dev"
Requires-Dist: black>=23.0.0; extra == "dev"
Requires-Dist: isort>=5.12.0; extra == "dev"
Requires-Dist: respx>=0.20.0; extra == "dev"
Dynamic: license-file
